norminette_prune/__init__.py
norminette_prune/main.py
norminette_prune/rules/content_python_file/check_basemodel_in_payloads.py
norminette_prune/rules/content_python_file/check_core_model_usage.py
norminette_prune/rules/content_python_file/check_missing_str_method.py
norminette_prune/rules/content_python_file/check_textchoices_in_enums.py
norminette_prune/rules/content_python_file/check_urls_name_parameter.py
norminette_prune/rules/content_python_file/check_view_function_naming.py
norminette_prune/rules/files_emplacement/check_pages_folder_structure.py
norminette_prune/rules/files_emplacement/check_templates_static_structure.py
norminette_prune/rules/formate/normalize_django_tags_spacing.py
norminette_prune/rules/formate/remove_double_empty_lines.py
norminette_prune/rules/project_config/check_environment_class_in_settings.py
norminette_prune/rules/project_config/check_for_envsettings_class_in_settings.py
norminette_prune/rules/project_config/check_gitignore_content.py
norminette_prune/rules/project_config/check_pyproject_configuration.py
norminette_prune/rules/project_config/check_uv_use.py
norminette_prune/rules/project_config/check_valid_whitenoise_and_static_paths.py
norminette_prune/rules/project_config/utils/read_settings.py
norminette_prune/rules/templates/check_component_and_layout_file_placement.py
norminette_prune/rules/templates/check_svg_files_location_and_extension.py
norminette_prune/rules/templates/check_svg_inclusion_paths.py
norminette_prune/utils/display_result.py
norminette_prune/utils/run_checks.py
norminette_prune/utils/setup_django.py
norminette_prune/utils/rules/display_rules.py
norminette_prune/utils/rules/extract_rules.py
norminette_prune/utils/rules/generate_readme.py
norminette_prune-1.2.7.dist-info/METADATA
norminette_prune-1.2.7.dist-info/WHEEL
norminette_prune-1.2.7.dist-info/entry_points.txt
norminette_prune-1.2.7.dist-info/top_level.txt
norminette_prune-1.2.7.dist-info/RECORD
